texttool/__init__.py
texttool/texttool.py
texttool-0.0.3.dist-info/LICENSE
texttool-0.0.3.dist-info/METADATA
texttool-0.0.3.dist-info/WHEEL
texttool-0.0.3.dist-info/top_level.txt
texttool-0.0.3.dist-info/RECORD
