Metadata-Version: 2.1
Name: texttool
Version: 0.0.3
Summary: Library for wrapping text to widths
Home-page: https://github.com/dantechguy/texttool
Author: Dan W-B
Author-email: d@nielwb.com
License: UNKNOWN
Platform: UNKNOWN
Classifier: Programming Language :: Python :: 3
Classifier: License :: OSI Approved :: MIT License
Classifier: Operating System :: OS Independent
Requires-Python: >=3.6
License-File: LICENSE
